{
  "status": "pass",
  "multiwork_candidate_references": [
    {
      "path": "docs/architecture/stage129_blueprint.md",
      "terms": [
        "MultiWork",
        "MultiWorkCIM",
        "SharedCharacterDB",
        "SharedWorldDB",
        "shared world"
      ]
    },
    {
      "path": "docs/architecture/stage130_blueprint.md",
      "terms": [
        "MultiWork",
        "MultiWorkCIM",
        "SharedWorldDB",
        "V571"
      ]
    },
    {
      "path": "docs/architecture/stage131_blueprint.md",
      "terms": [
        "MultiWork"
      ]
    },
    {
      "path": "docs/proposals/stage129_proposal.md",
      "terms": [
        "MultiWork",
        "MultiWorkCIM"
      ]
    },
    {
      "path": "docs/proposals/stage130_proposal.md",
      "terms": [
        "MultiWork"
      ]
    },
    {
      "path": "docs/proposals/stage131_proposal.md",
      "terms": [
        "MultiWork"
      ]
    },
    {
      "path": "docs/sessions/2026-05-19_home_session_summary.md",
      "terms": [
        "V571"
      ]
    },
    {
      "path": "docs/stages/stage127.md",
      "terms": [
        "MultiWork",
        "SharedCharacterDB",
        "SharedWorldDB",
        "V571"
      ]
    },
    {
      "path": "docs/stages/stage128.md",
      "terms": [
        "MultiWork",
        "MultiWorkCIM",
        "SharedCharacterDB",
        "SharedWorldDB",
        "V571"
      ]
    },
    {
      "path": "docs/stages/stage129.md",
      "terms": [
        "MultiWork",
        "MultiWorkCIM",
        "SharedCharacterDB",
        "SharedWorldDB",
        "shared world"
      ]
    },
    {
      "path": "docs/stages/stage130.md",
      "terms": [
        "MultiWork",
        "MultiWorkCIM",
        "V571"
      ]
    },
    {
      "path": "docs/stages/STAGE_INDEX.md",
      "terms": [
        "MultiWork",
        "MultiWorkCIM"
      ]
    },
    {
      "path": "docs/generated/wiki/stage_lineage_wiki.md",
      "terms": [
        "MultiWork",
        "MultiWorkCIM"
      ]
    },
    {
      "path": "manifests/stage127_branchpoint_trace_manifest.json",
      "terms": [
        "MultiWork"
      ]
    },
    {
      "path": "manifests/stage127_manifest.json",
      "terms": [
        "MultiWork",
        "V571"
      ]
    },
    {
      "path": "manifests/stage127_multiwork_preflight_manifest.json",
      "terms": [
        "MultiWork",
        "V571"
      ]
    },
    {
      "path": "manifests/stage128_read_only_absorption_manifest.json",
      "terms": [
        "MultiWork",
        "MultiWorkCIM",
        "SharedWorldDB"
      ]
    },
    {
      "path": "manifests/stage129_branchpoint_trace_manifest.json",
      "terms": [
        "MultiWork"
      ]
    },
    {
      "path": "manifests/stage129_manifest.json",
      "terms": [
        "MultiWork",
        "MultiWorkCIM"
      ]
    },
    {
      "path": "manifests/stage129_multiwork_cim_governor_manifest.json",
      "terms": [
        "MultiWork",
        "MultiWorkCIM"
      ]
    },
    {
      "path": "manifests/stage130_branchpoint_trace_manifest.json",
      "terms": [
        "MultiWork"
      ]
    },
    {
      "path": "manifests/stage130_manifest.json",
      "terms": [
        "MultiWork"
      ]
    },
    {
      "path": "manifests/stage130_multiwork_release_manifest.json",
      "terms": [
        "MultiWork",
        "V571"
      ]
    },
    {
      "path": "manifests/stage131_branchpoint_trace_manifest.json",
      "terms": [
        "MultiWork"
      ]
    },
    {
      "path": "manifests/stage_lineage_manifest.json",
      "terms": [
        "MultiWork",
        "MultiWorkCIM"
      ]
    },
    {
      "path": "release/current/stage127_developer_handoff.md",
      "terms": [
        "MultiWork",
        "SharedCharacterDB",
        "SharedWorldDB",
        "V571"
      ]
    },
    {
      "path": "release/current/stage127_execution_report.json",
      "terms": [
        "MultiWork",
        "V571"
      ]
    },
    {
      "path": "release/current/stage127_multiwork_preflight_report.json",
      "terms": [
        "AuthorLicenseAPI",
        "CrossWork",
        "MultiWork",
        "MultiWorkCIM",
        "MultiWorkOrchestrator",
        "ProjectIsolationManager",
        "SharedCharacterDB",
        "SharedWorldDB",
        "V571",
        "shared character",
        "shared world"
      ]
    },
    {
      "path": "release/current/stage127_release_gate_report.json",
      "terms": [
        "MultiWork",
        "V571"
      ]
    },
    {
      "path": "release/current/stage127_summary.json",
      "terms": [
        "MultiWork",
        "MultiWorkCIM",
        "V571"
      ]
    },
    {
      "path": "release/current/stage128_read_only_absorption_report.json",
      "terms": [
        "V571"
      ]
    },
    {
      "path": "release/current/stage128_summary.json",
      "terms": [
        "MultiWork",
        "MultiWorkCIM"
      ]
    },
    {
      "path": "release/current/stage129_multiwork_cim_governor_report.json",
      "terms": [
        "MultiWork",
        "MultiWorkCIM"
      ]
    },
    {
      "path": "release/current/stage129_release_gate_report.json",
      "terms": [
        "MultiWork",
        "MultiWorkCIM"
      ]
    },
    {
      "path": "release/current/stage129_summary.json",
      "terms": [
        "MultiWork",
        "MultiWorkCIM"
      ]
    },
    {
      "path": "release/current/stage130_multiwork_release_report.json",
      "terms": [
        "MultiWork",
        "MultiWorkCIM",
        "V571"
      ]
    },
    {
      "path": "release/current/stage130_release_gate_report.json",
      "terms": [
        "MultiWork",
        "V571"
      ]
    },
    {
      "path": "release/current/stage130_summary.json",
      "terms": [
        "MultiWork"
      ]
    },
    {
      "path": "release/current/stage131_gig_advisory_report.json",
      "terms": [
        "MultiWork"
      ]
    },
    {
      "path": "release/current/stage132_contradiction_classifier_report.json",
      "terms": [
        "MultiWork"
      ]
    },
    {
      "path": "release/current/stage145_body_constitution_report.json",
      "terms": [
        "MultiWork",
        "shared world"
      ]
    },
    {
      "path": "release/current/stage127_multiwork_preflight_pack/absorption_plan.json",
      "terms": [
        "MultiWork",
        "MultiWorkCIM",
        "ProjectIsolationManager",
        "SharedWorldDB"
      ]
    },
    {
      "path": "release/current/stage127_multiwork_preflight_pack/gitnexus_preflight_snapshot.json",
      "terms": [
        "MultiWork"
      ]
    },
    {
      "path": "release/current/stage127_multiwork_preflight_pack/multiwork_risk_matrix.json",
      "terms": [
        "ProjectIsolationManager",
        "V571"
      ]
    },
    {
      "path": "release/current/stage127_multiwork_preflight_pack/multiwork_scanner_report.json",
      "terms": [
        "AuthorLicenseAPI",
        "CrossWork",
        "MultiWork",
        "MultiWorkCIM",
        "MultiWorkOrchestrator",
        "ProjectIsolationManager",
        "SharedCharacterDB",
        "SharedWorldDB",
        "V571",
        "shared character",
        "shared world"
      ]
    },
    {
      "path": "release/current/stage127_multiwork_preflight_pack/python_fallback_report.json",
      "terms": [
        "MultiWork"
      ]
    },
    {
      "path": "release/current/stage129_multiwork_cim_governor_pack/cross_project_influence_report.json",
      "terms": [
        "MultiWork",
        "MultiWorkCIM"
      ]
    },
    {
      "path": "release/current/stage129_multiwork_cim_governor_pack/gitnexus_preflight_report.json",
      "terms": [
        "MultiWork"
      ]
    },
    {
      "path": "release/current/stage129_multiwork_cim_governor_pack/stage129_summary.json",
      "terms": [
        "MultiWork",
        "MultiWorkCIM"
      ]
    },
    {
      "path": "release/current/stage130_multiwork_release_pack/gitnexus_preflight_report.json",
      "terms": [
        "MultiWork"
      ]
    },
    {
      "path": "release/current/stage130_multiwork_release_pack/operational_surface_report.json",
      "terms": [
        "MultiWork",
        "V571"
      ]
    },
    {
      "path": "release/current/stage130_multiwork_release_pack/release_matrix_report.json",
      "terms": [
        "MultiWork",
        "MultiWorkCIM",
        "V571"
      ]
    },
    {
      "path": "release/current/stage130_multiwork_release_pack/release_seal_report.json",
      "terms": [
        "MultiWork"
      ]
    },
    {
      "path": "release/current/stage130_multiwork_release_pack/stage130_summary.json",
      "terms": [
        "MultiWork"
      ]
    },
    {
      "path": "release/current/stage131_gig_advisory_pack/gitnexus_preflight_report.json",
      "terms": [
        "MultiWork"
      ]
    },
    {
      "path": "release/current/stage132_contradiction_classifier_pack/gitnexus_preflight_report.json",
      "terms": [
        "MultiWork"
      ]
    },
    {
      "path": "release/current/stage145_body_constitution_pack/formula_classification.json",
      "terms": [
        "MultiWork",
        "shared world"
      ]
    },
    {
      "path": "release/current/stage99_gitnexus_pack/impact_nodes.json",
      "terms": [
        "MultiWork"
      ]
    }
  ],
  "candidate_reference_count": 58,
  "direct_v571_merge_detected": false,
  "direct_merge_paths_present": [],
  "scan_terms": [
    "V571",
    "MultiWork",
    "SharedCharacterDB",
    "SharedWorldDB",
    "ProjectIsolationManager",
    "MultiWorkCIM",
    "AuthorLicenseAPI",
    "MultiWorkOrchestrator",
    "CrossWork",
    "shared character",
    "shared world"
  ]
}
